EMAI/__init__.py
EMAI/ML/ML.py
EMAI/ML/__init__.py
EMAI/loaders/__init__.py
EMAI/loaders/loaders.py
EMAI/tools4D/__init__.py
EMAI/tools4D/tools4D.py
EMAI/toolsEELS/__init__.py
EMAI/toolsEELS/toolsEELS.py
EMAI/utils/__init__.py
EMAI/utils/utils.py
EMAI-0.1.8.dist-info/METADATA
EMAI-0.1.8.dist-info/WHEEL
EMAI-0.1.8.dist-info/top_level.txt
EMAI-0.1.8.dist-info/RECORD
