Metadata-Version: 2.1
Name: EMAI
Version: 0.1.8
Summary: Electron microscopy AI tools
Home-page: UNKNOWN
Author: Kevin M. Roccapriore
License: UNKNOWN
Keywords: EMAI,pycroscopy,atomai,stemtool
Platform: UNKNOWN
Requires-Python: ~=3.6
Requires-Dist: matplotlib (<3.4,>=3.2)
Requires-Dist: numpy (>=1.18.5)
Requires-Dist: scipy (>=1.3.0)
Requires-Dist: torch (>=1.0.0)
Requires-Dist: scikit-image (>=0.16.2)
Requires-Dist: opencv-python (>=4.1.0)
Requires-Dist: scikit-learn (>=0.22.1)
Requires-Dist: atomai (>=0.7.0)
Requires-Dist: networkx (>=2.5mendeleev<=0.6.1)
Requires-Dist: torchvision (>=0.8.0)
Requires-Dist: gpytorch (>=1.4.0)
